dagmc_geometry_slice_plotter/__init__.py
dagmc_geometry_slice_plotter/_version.py
dagmc_geometry_slice_plotter/app.py
dagmc_geometry_slice_plotter/core.py
dagmc_geometry_slice_plotter/launch.py
dagmc_geometry_slice_plotter/utils.py
dagmc_geometry_slice_plotter-0.3.1.dist-info/LICENSE.txt
dagmc_geometry_slice_plotter-0.3.1.dist-info/METADATA
dagmc_geometry_slice_plotter-0.3.1.dist-info/WHEEL
dagmc_geometry_slice_plotter-0.3.1.dist-info/entry_points.txt
dagmc_geometry_slice_plotter-0.3.1.dist-info/top_level.txt
dagmc_geometry_slice_plotter-0.3.1.dist-info/RECORD
