Metadata-Version: 2.1
Name: dagmc-geometry-slice-plotter
Version: 0.3.1
Summary: A minimal Python package for creating plots of slices through DAGMC geometry
Author-email: Jonathan Shimwell <mail@jshimwell.com>
License: MIT License
Project-URL: Homepage, https://github.com/fusion-energy/dagmc_geometry_slice_plotter
Project-URL: Bug Tracker, https://github.com/fusion-energy/dagmc_geometry_slice_plotter/issues
Keywords: dagmc,geometry,plot,slice
Classifier: Programming Language :: Python :: 3
Classifier: License :: OSI Approved :: MIT License
Classifier: Operating System :: OS Independent
Requires-Python: >=3.8
License-File: LICENSE.txt
Requires-Dist: matplotlib
Requires-Dist: trimesh
Requires-Dist: shapely
Requires-Dist: scipy
Requires-Dist: meshio
Requires-Dist: h5py
Requires-Dist: streamlit
Provides-Extra: tests
Requires-Dist: pytest ; extra == 'tests'
Requires-Dist: pytest-cov ; extra == 'tests'
